ddplt/__init__.py
ddplt/classification.py
ddplt/heatmaps.py
ddplt/test_base.py
ddplt/test_classification.py
ddplt/test_heatmaps.py
ddplt/test_misc.py
ddplt-0.0.2.dist-info/LICENSE
ddplt-0.0.2.dist-info/METADATA
ddplt-0.0.2.dist-info/WHEEL
ddplt-0.0.2.dist-info/top_level.txt
ddplt-0.0.2.dist-info/RECORD
