Metadata-Version: 2.1
Name: ddplt
Version: 0.0.2
Summary: A package with code from my ML projects that has a potential of being reusable
Home-page: https://github.com/ielis/ddplt
Author: Daniel Danis
Author-email: daniel.gordon.danis@gmail.com
License: GPLv3
Keywords: plotting machine learning evaluation metrics
Platform: UNKNOWN
Requires-Dist: matplotlib (>=3.1.0)
Requires-Dist: scikit-learn (>=0.22)
Requires-Dist: numpy (>=1.18)
Requires-Dist: pandas (>=1.0.0)
Requires-Dist: scipy (>=1.5.0)
Requires-Dist: ddconst (>=0.0.2)
